pyfvs/README.txt
pyfvs/__init__.py
pyfvs/__main__.py
pyfvs/_c_mensfuncs.pyd
pyfvs/_version.py
pyfvs/fvs.py
pyfvs/pyfvs.cfg
pyfvs/pyfvscac.pyd
pyfvs/pyfvsecc.pyd
pyfvs/pyfvsoc.pyd
pyfvs/pyfvsop.pyd
pyfvs/pyfvspnc.pyd
pyfvs/pyfvssoc.pyd
pyfvs/pyfvswcc.pyd
pyfvs/docs/pyfvscac.html
pyfvs/docs/pyfvsecc.html
pyfvs/docs/pyfvsoc.html
pyfvs/docs/pyfvsop.html
pyfvs/docs/pyfvspnc.html
pyfvs/docs/pyfvssoc.html
pyfvs/docs/pyfvswcc.html
pyfvs/docs/readme.rst
pyfvs/examples/demo.key
pyfvs/examples/demo.py
pyfvs/examples/demo.tre
pyfvs/examples/pn_test.key
pyfvs/examples/pn_test.py
pyfvs/examples/pn_test.tre
pyfvs/keywords/__init__.py
pyfvs/keywords/_fields.py
pyfvs/keywords/_utils.py
pyfvs/keywords/eventmonitor.py
pyfvs/keywords/keywords.py
pyfvs/test/__init__.py
pyfvs/test/test_fvstrees.py
pyfvs/test/test_treedata.py
pyfvs/test/test_variants.py
pyfvs/test/rmrs/ca_bareground.key
pyfvs/test/rmrs/ca_bareground.sum.save
pyfvs/test/rmrs/ec_bareground.key
pyfvs/test/rmrs/ec_bareground.sum.save
pyfvs/test/rmrs/oc_bareground.key
pyfvs/test/rmrs/oc_bareground.sum.save
pyfvs/test/rmrs/op_bareground.key
pyfvs/test/rmrs/op_bareground.sum.save
pyfvs/test/rmrs/pn_bareground.key
pyfvs/test/rmrs/pn_bareground.sum.save
pyfvs/test/rmrs/so_bareground.key
pyfvs/test/rmrs/so_bareground.sum.save
pyfvs/test/rmrs/wc_bareground.key
pyfvs/test/rmrs/wc_bareground.sum.save
pyfvs-0.0.13.dist-info/DESCRIPTION.rst
pyfvs-0.0.13.dist-info/METADATA
pyfvs-0.0.13.dist-info/RECORD
pyfvs-0.0.13.dist-info/WHEEL
pyfvs-0.0.13.dist-info/entry_points.txt
pyfvs-0.0.13.dist-info/metadata.json
pyfvs-0.0.13.dist-info/top_level.txt
