Metadata-Version: 2.0
Name: pyfvs
Version: 0.0.13
Summary: PyFVS - Python wrappers for Open-FVS.
Home-page: https://github.com/tharen/PyFVS
Author: Tod Haren
Author-email: tod.haren@gmail.com
License: UNKNOWN
Download-URL: https://github.com/tharen/PyFVS/archive/master.zip
Platform: UNKNOWN
Classifier: Development Status :: 3 - Alpha
Classifier: Environment :: Console
Classifier: Intended Audience :: Developers
Classifier: Intended Audience :: End Users/Desktop
Classifier: Intended Audience :: Science/Research
Classifier: Natural Language :: English
Classifier: Programming Language :: Python
Classifier: Programming Language :: Fortran
Requires-Dist: matplotlib
Requires-Dist: numpy (>=1.11)
Requires-Dist: pandas
